<mods xmlns="http://www.loc.gov/mods/v3" xmlns:mods="http://www.loc.gov/mods/v3" xmlns:xlink="http://www.w3.org/1999/xlink" xmlns:xsi="http://www.w3.org/2001/XMLSchema-instance"><titleInfo><title>Phi Sigma Delta Fraternity</title></titleInfo><name type="personal"><role><roleTerm type="text">creator</roleTerm></role></name><typeOfResource>still image</typeOfResource><originInfo><publisher>University of Denver</publisher><place><placeTerm type="text">Denver, Colorado</placeTerm></place><dateCreated keyDate="yes">1934</dateCreated></originInfo><language><languageTerm type="text">Inscription is in English.</languageTerm></language><physicalDescription><extent>1 item (photograph), 4 x 5 inches, black and white</extent><note>Handwritten on back of photograph: ''Phi Sigma Delta Fraternity, 1934 - Boulder Chapter - Theta, #387.''  Handwritten on paper with photograph: ''Phi Sigma Delta Fraternity, 1934 -  Boulder Chapter - Theta, #387, Left to Right, Top Row - Edward N. Bronstein, Gerald Rosenblum, Philip Hornbein, Myron Goldberg, Harry H. Frumess, Milton Morris; Next to Top Row, Edward Pringle, Edward Mellicker, Irving Hayutin, Sam Rifkin, Leonard Leff, Richard Saliman, Louis Dubin; Next to Bottom Row, Sampson Knoll, Ray Katz, David Weinberg; Bottom Row, Alvin Lichenstein, Edmond Frank Graber, Joseph A. Eisenberg, Hyman Chester, Harold Gilman, Francis Reibscheid; Mascot - Romeo.''</note><form>Photographic prints</form></physicalDescription><abstract>A group of young men pose together on the steps of an unidentified building with an older man and a dog, their mascot named Romeo.  Top row left to right, Edward N. Bronstein, Gerald Rosenblum, Philip Hornbein, Myron Goldberg, Harry A. Frumess, and Milton Morris.  Next to top row left to right, Edward Pringle, Edward Mellicker, Irving Hayutin, Sam Rifkin, Leonard Leff, Richard Saliman, and Louis Dubin.  Next to bottom row left to right, Sampson Knoll, Ray Katz, and David Weinberg.  Bottom Row left to right, Alvin Lichenstein, Edmond Frank Graber, Joseph A. Eisenberg, Hyman Chester, Harold Gilman, and Francis Reibscheid.</abstract><note>Title supplied by archivist.</note><note type="admin">Donated by Faye Greenberg Schayer</note><note type="admin">ph387</note><subject><name type="personal"><namePart>Hornbein, Philip,--1915-1987</namePart></name></subject><subject><name type="personal"><namePart>Frumess, Harry A.</namePart></name></subject><subject><name type="personal"><namePart>Morris, Milton</namePart></name></subject><subject><name type="personal"><namePart>Pringle, Edward E.</namePart></name></subject><subject><name type="personal"><namePart>Hayutin, Irving J.,--1917-2001</namePart></name></subject><subject><name type="personal"><namePart>Saliman, Richard S. (Dick)--1915-2010</namePart></name></subject><subject><name type="personal"><namePart>Bronstein, Edward N.</namePart></name></subject><subject><name type="personal"><namePart>Rosenblum, Gerald</namePart></name></subject><subject><name type="personal"><namePart>Goldberg, Myron</namePart></name></subject><subject><name type="personal"><namePart>Rifkin, Sam</namePart></name></subject><subject><name type="personal"><namePart>Leff, Leonard</namePart></name></subject><subject><name type="personal"><namePart>Dublin, Louis</namePart></name></subject><subject><name type="personal"><namePart>Knoll, Sampson</namePart></name></subject><subject><name type="personal"><namePart>Katz, Ray</namePart></name></subject><subject><name type="personal"><namePart>Weinberg, David</namePart></name></subject><subject><name type="personal"><namePart>Lichenstein, Alvin</namePart></name></subject><subject><name type="personal"><namePart>Graber, Edmond Frank</namePart></name></subject><subject><name type="personal"><namePart>Eisenberg, Joseph A.</namePart></name></subject><subject><name type="personal"><namePart>Chester, Hyman</namePart></name></subject><subject><name type="personal"><namePart>Gilman, Harold</namePart></name></subject><subject><name type="personal"><namePart>Reibscheid, Francis</namePart></name></subject><subject><name type="personal"><namePart>Mellicker, Edward</namePart></name></subject><subject><name type="corporate"><namePart>Phi Sigma Delta</namePart></name></subject><subject></subject><subject></subject><subject></subject><subject></subject><subject></subject><subject></subject><relatedItem><titleInfo><title>Beck Archives Photograph Collection, Organizations</title></titleInfo></relatedItem><identifier type="local">B063.04.0020.00001</identifier><location><url usage="primary display">http://hdl.handle.net/10176/codu:64022</url></location><accessCondition type="useAndReproduction">Copyright restrictions may apply. User is responsible for all copyright compliance.</accessCondition></mods>