<mods xmlns="http://www.loc.gov/mods/v3" xmlns:mods="http://www.loc.gov/mods/v3" xmlns:xlink="http://www.w3.org/1999/xlink" xmlns:xsi="http://www.w3.org/2001/XMLSchema-instance"><titleInfo><title>Denrow - PHD - 2012 - Letter</title></titleInfo><name type="personal"><namePart>Denrow, Jennifer</namePart><role><roleTerm authority="marcrelator" type="text">Author</roleTerm></role></name><typeOfResource>text</typeOfResource><identifier type="hdl">http://hdl.handle.net/10176/codu:78329</identifier></mods>